lucidx/__init__.py
lucidx/banr.py
lucidx/colors.py
lucidx/genx.py
lucidx/main.py
lucidx/modulex.py
lucidx-1.0.4.dist-info/licenses/LICENSE
lucidx-1.0.4.dist-info/METADATA
lucidx-1.0.4.dist-info/WHEEL
lucidx-1.0.4.dist-info/entry_points.txt
lucidx-1.0.4.dist-info/top_level.txt
lucidx-1.0.4.dist-info/RECORD
