Metadata-Version: 2.4
Name: lucidx
Version: 1.0.4
Summary: AI-powered image synthesis engine using Stability AI API
Home-page: https://github.com/VritraSecz/LucidX
Author: Alex Butler [Vritra Security Organization]
License: MIT
Project-URL: Homepage, https://github.com/VritraSecz/LucidX
Project-URL: Bug Tracker, https://github.com/VritraSecz/LucidX/issues
Project-URL: Documentation, https://github.com/VritraSecz/LucidX#readme
Project-URL: Source Code, https://github.com/VritraSecz/LucidX
Project-URL: Telegram, https://t.me/LinkCentralX
Project-URL: Website, https://vritrasec.com
Keywords: ai,artificial-intelligence,image-generation,stability-ai,text-to-image,image-synthesis,cli,tool,python,machine-learning,deep-learning,creative,art,digital-art
Platform: any
Classifier: Development Status :: 5 - Production/Stable
Classifier: Intended Audience :: Developers
Classifier: Intended Audience :: End Users/Desktop
Classifier: Topic :: Multimedia :: Graphics
Classifier: Topic :: Artistic Software
Classifier: Topic :: Scientific/Engineering :: Artificial Intelligence
Classifier: License :: OSI Approved :: MIT License
Classifier: Programming Language :: Python :: 3
Classifier: Programming Language :: Python :: 3.7
Classifier: Programming Language :: Python :: 3.8
Classifier: Programming Language :: Python :: 3.9
Classifier: Programming Language :: Python :: 3.10
Classifier: Programming Language :: Python :: 3.11
Classifier: Programming Language :: Python :: 3.12
Classifier: Operating System :: OS Independent
Classifier: Operating System :: POSIX :: Linux
Classifier: Operating System :: MacOS
Classifier: Operating System :: Microsoft :: Windows
Classifier: Environment :: Console
Classifier: Natural Language :: English
Requires-Python: >=3.7
License-File: LICENSE
Requires-Dist: colorama>=0.4.4
Requires-Dist: requests>=2.25.1
Provides-Extra: dev
Requires-Dist: pytest>=6.0; extra == "dev"
Requires-Dist: black>=21.0; extra == "dev"
Requires-Dist: flake8>=3.8; extra == "dev"
Requires-Dist: twine>=3.0; extra == "dev"
Dynamic: home-page
Dynamic: license-file
Dynamic: platform
Dynamic: requires-python
